energy_consumption_forecasting/__init__.py
energy_consumption_forecasting/airflow/__init__.py
energy_consumption_forecasting/airflow/dags/__init__.py
energy_consumption_forecasting/airflow/dags/utils.py
energy_consumption_forecasting/airflow/dags/workflow_pipeline_dag.py
energy_consumption_forecasting/airflow/docker-compose.yaml
energy_consumption_forecasting/airflow/Dockerfile
energy_consumption_forecasting/exceptions.py
energy_consumption_forecasting/feature_pipeline/__init__.py
energy_consumption_forecasting/feature_pipeline/data_extraction.py
energy_consumption_forecasting/feature_pipeline/data_loading.py
energy_consumption_forecasting/feature_pipeline/data_transformation.py
energy_consumption_forecasting/feature_pipeline/data_validation.py
energy_consumption_forecasting/feature_pipeline/feature_pipeline.py
energy_consumption_forecasting/feature_pipeline/feature_view.py
energy_consumption_forecasting/feature_pipeline/tests/test_data_extraction.py
energy_consumption_forecasting/feature_pipeline/tests/test_data_transformation.py
energy_consumption_forecasting/inference_pipeline/__init__.py
energy_consumption_forecasting/inference_pipeline/batch_data.py
energy_consumption_forecasting/inference_pipeline/inference_pipeline.py
energy_consumption_forecasting/inference_pipeline/monitor_performance.py
energy_consumption_forecasting/inference_pipeline/utils.py
energy_consumption_forecasting/logger.py
energy_consumption_forecasting/training_pipeline/__init__.py
energy_consumption_forecasting/training_pipeline/data_preprocessing.py
energy_consumption_forecasting/training_pipeline/hyperparameter_tuning.py
energy_consumption_forecasting/training_pipeline/model_builder.py
energy_consumption_forecasting/training_pipeline/training_pipeline.py
energy_consumption_forecasting/training_pipeline/utils.py
energy_consumption_forecasting/utils.py
energy_consumption_forecasting-0.2.1.dist-info/LICENSE
energy_consumption_forecasting-0.2.1.dist-info/METADATA
energy_consumption_forecasting-0.2.1.dist-info/WHEEL
energy_consumption_forecasting-0.2.1.dist-info/RECORD
